LICENSE
MANIFEST.in
README.rst
setup.py
pynuodb/__init__.py
pynuodb/calendar.py
pynuodb/connection.py
pynuodb/crypt.py
pynuodb/cursor.py
pynuodb/datatype.py
pynuodb/encodedsession.py
pynuodb/exception.py
pynuodb/protocol.py
pynuodb/result_set.py
pynuodb/session.py
pynuodb/statement.py
pynuodb.egg-info/PKG-INFO
pynuodb.egg-info/SOURCES.txt
pynuodb.egg-info/dependency_links.txt
pynuodb.egg-info/requires.txt
pynuodb.egg-info/top_level.txt