Metadata-Version: 2.1
Name: pynuodb
Version: 4.0.0
Summary: NuoDB Python driver
Home-page: https://github.com/nuodb/nuodb-python
Author: NuoDB
Author-email: drivers@nuodb.com
License: BSD License
Keywords: nuodb scalable cloud database
Platform: UNKNOWN
Classifier: Development Status :: 5 - Production/Stable
Classifier: Environment :: Console
Classifier: Intended Audience :: Developers
Classifier: License :: OSI Approved :: BSD License
Classifier: Operating System :: OS Independent
Classifier: Programming Language :: Python
Classifier: Programming Language :: Python :: 2
Classifier: Programming Language :: Python :: 2.7
Classifier: Programming Language :: Python :: 3
Classifier: Programming Language :: Python :: 3.6
Classifier: Programming Language :: SQL
Classifier: Topic :: Database :: Front-Ends
Provides-Extra: crypto
